[
    {
        "User": "Michael Bennet",
        "Followers": "12500",
        "Following": "39",
        "Posts": "411"
    },
    {
        "User": "Joe Biden",
        "Followers": "1400000",
        "Following": "19",
        "Posts": "254"
    },
    {
        "User": "Mike Bloomberg",
        "Followers": "268000",
        "Following": "33",
        "Posts": "1098"
    },
    {
        "User": "Pete Buttigieg",
        "Followers": "1000000",
        "Following": "1174",
        "Posts": "531"
    },
    {
        "User": "John Delaney",
        "Followers": "6244",
        "Following": "308",
        "Posts": "518"
    },
    {
        "User": "Tulsi Gabbard",
        "Followers": "281800",
        "Following": "544",
        "Posts": "1555"
    },
    {
        "User": "Amy Klobuchar",
        "Followers": "159000",
        "Following": "395",
        "Posts": "719"
    },
    {
        "User": "Deval Patrick",
        "Followers": "3177",
        "Following": "7",
        "Posts": "53"
    },
    {
        "User": "Bernie Sanders",
        "Followers": "4100000",
        "Following": "1967",
        "Posts": "196"
    },
    {
        "User": "Tom Steyer",
        "Followers": "66600",
        "Following": "491",
        "Posts": "428"
    },
    {
        "User": "Elizabeth Warren",
        "Followers": "2200000",
        "Following": "53",
        "Posts": "1610"
    },
    {
        "User": "Andrew Yang",
        "Followers": "540400",
        "Following": "83",
        "Posts": "1432"
    },
    {
        "User": "Donald Trump",
        "Followers": "17000000",
        "Following": "8",
        "Posts": "5280"
    },
    {
        "User": "Joe Walsh",
        "Followers": "6864",
        "Following": "5792",
        "Posts": "170"
    },
    {
        "User": "Bill Weld",
        "Followers": "16600",
        "Following": "27",
        "Posts": "51"
    }
]
